filterpy/__init__.py
filterpy/common/__init__.py
filterpy/common/discretization.py
filterpy/common/helpers.py
filterpy/common/kinematic.py
filterpy/discrete_bayes/__init__.py
filterpy/discrete_bayes/discrete_bayes.py
filterpy/examples/GetRadar.py
filterpy/examples/RadarUKF.py
filterpy/examples/__init__.py
filterpy/examples/bearing_only.py
filterpy/examples/radar_sim.py
filterpy/gh/__init__.py
filterpy/gh/gh_filter.py
filterpy/hinfinity/__init__.py
filterpy/hinfinity/hinfinity_filter.py
filterpy/kalman/CubatureKalmanFilter.py
filterpy/kalman/EKF.py
filterpy/kalman/IMM.py
filterpy/kalman/UKF.py
filterpy/kalman/__init__.py
filterpy/kalman/ensemble_kalman_filter.py
filterpy/kalman/fading_memory.py
filterpy/kalman/fixed_lag_smoother.py
filterpy/kalman/information_filter.py
filterpy/kalman/kalman_filter.py
filterpy/kalman/mmae.py
filterpy/kalman/sigma_points.py
filterpy/kalman/square_root.py
filterpy/kalman/unscented_transform.py
filterpy/leastsq/__init__.py
filterpy/leastsq/least_squares.py
filterpy/memory/__init__.py
filterpy/memory/fading_memory.py
filterpy/monte_carlo/__init__.py
filterpy/monte_carlo/resampling.py
filterpy/stats/__init__.py
filterpy/stats/stats.py
filterpywhl-1.4.5.dist-info/LICENSE
filterpywhl-1.4.5.dist-info/METADATA
filterpywhl-1.4.5.dist-info/WHEEL
filterpywhl-1.4.5.dist-info/top_level.txt
filterpywhl-1.4.5.dist-info/RECORD
